MANIFEST.in
README.rst
package.json
setup.cfg
setup.py
awsume/__init__.py
awsume/autoawsume.py
awsume/awsumepy.py
awsume/test_autoawsume.py
awsume/test_awsumepy.py
awsume/shellScripts/awsume
awsume/shellScripts/awsume.bat
awsume/shellScripts/awsume.ps1
awsume_cygwin.egg-info/PKG-INFO
awsume_cygwin.egg-info/SOURCES.txt
awsume_cygwin.egg-info/dependency_links.txt
awsume_cygwin.egg-info/entry_points.txt
awsume_cygwin.egg-info/requires.txt
awsume_cygwin.egg-info/top_level.txt